setup.py
django_prometheus_metrics/__init__.py
django_prometheus_metrics/apps.py
django_prometheus_metrics/middleware.py
django_prometheus_metrics/models.py
django_prometheus_metrics/urls.py
django_prometheus_metrics/views.py
django_prometheus_metrics.egg-info/PKG-INFO
django_prometheus_metrics.egg-info/SOURCES.txt
django_prometheus_metrics.egg-info/dependency_links.txt
django_prometheus_metrics.egg-info/requires.txt
django_prometheus_metrics.egg-info/top_level.txt
django_prometheus_metrics/tests/__init__.py
django_prometheus_metrics/tests/tests.py